nile_verifier/__init__.py
nile_verifier/api.py
nile_verifier/main.py
nile_verifier-0.1.5.dist-info/entry_points.txt
nile_verifier-0.1.5.dist-info/LICENSE
nile_verifier-0.1.5.dist-info/WHEEL
nile_verifier-0.1.5.dist-info/METADATA
nile_verifier-0.1.5.dist-info/RECORD
