Metadata-Version: 2.1
Name: nile-verifier
Version: 0.1.5
Summary: Nile plugin to verify smart contracts on starkscan.co
Home-page: https://github.com/martriay/nile-verifier-plugin
License: MIT
Keywords: cairo,nile
Author: Martín Triay
Author-email: martriay@gmail.com
Requires-Python: >=3.8,<3.10
Classifier: License :: OSI Approved :: MIT License
Classifier: Programming Language :: Python :: 3
Classifier: Programming Language :: Python :: 3.8
Classifier: Programming Language :: Python :: 3.9
Requires-Dist: asyncclick (>=8.1.3.4,<9.0.0.0)
Requires-Dist: cairo-nile (>=0.11.0,<0.12.0)
Requires-Dist: click (>=8.1.3,<9.0.0)
Requires-Dist: requests (>=2.28.1,<3.0.0)
Requires-Dist: yaspin (>=2.2.0,<3.0.0)
Project-URL: Repository, https://github.com/martriay/nile-verifier-plugin
